decryptify/__init__.py
decryptify/cli.py
decryptify/core.py
decryptify-3.0.0.dist-info/METADATA
decryptify-3.0.0.dist-info/WHEEL
decryptify-3.0.0.dist-info/entry_points.txt
decryptify-3.0.0.dist-info/top_level.txt
decryptify-3.0.0.dist-info/RECORD
