Metadata-Version: 2.4
Name: decryptify
Version: 3.0.0
Summary: PDF password recovery tool
Author-email: d4niis44hir <eat_fir.0g@icloud.com>
Requires-Python: >=3.8
Requires-Dist: pikepdf
Requires-Dist: tqdm
